git_autosquash/__init__.py
git_autosquash/batch_git_ops.py
git_autosquash/blame_analyzer.py
git_autosquash/bounded_cache.py
git_autosquash/cli_strategy.py
git_autosquash/commit_history_analyzer.py
git_autosquash/exceptions.py
git_autosquash/git_native_complete_handler.py
git_autosquash/git_native_handler.py
git_autosquash/git_ops.py
git_autosquash/hunk_commit_splitter.py
git_autosquash/hunk_parser.py
git_autosquash/hunk_target_resolver.py
git_autosquash/main.py
git_autosquash/rebase_manager.py
git_autosquash/resource_managers.py
git_autosquash/result.py
git_autosquash/source_normalizer.py
git_autosquash/squash_context.py
git_autosquash/strategy_base.py
git_autosquash/validation.py
git_autosquash/tui/__init__.py
git_autosquash/tui/modern_app.py
git_autosquash/tui/modern_screens.py
git_autosquash/tui/state_controller.py
git_autosquash/tui/styles.py
git_autosquash/tui/ui_controllers.py
git_autosquash-0.1.0.dist-info/METADATA
git_autosquash-0.1.0.dist-info/WHEEL
git_autosquash-0.1.0.dist-info/entry_points.txt
git_autosquash-0.1.0.dist-info/RECORD
