Metadata-Version: 2.4
Name: git-autosquash
Version: 0.1.0
Summary: Automatically squash git changes back into historical commits
Author-email: Andrew Leech <andrew.leech@planetinnovation.com.au>
Requires-Python: >=3.12
Requires-Dist: pytest-textual-snapshot>=1.1.0
Requires-Dist: textual>=5.3.0
Requires-Dist: typer[all]>=0.12.0
